hydroponics/Basic_functions.py
hydroponics/Generate_Report.py
hydroponics/PH_Approximation_0.py
hydroponics/Refill_0.py
hydroponics/Solutions_Solubility.py
hydroponics/__init__.py
hydroponics/pH_graph_0.py
hydroponics/data/README.md
hydroponics/data/Solubility_data.csv
hydroponics/data/UserData.xlsx
hydroponics/data/molar_mass.csv
better_hydroponics-0.1.3.dist-info/LICENSE
better_hydroponics-0.1.3.dist-info/METADATA
better_hydroponics-0.1.3.dist-info/WHEEL
better_hydroponics-0.1.3.dist-info/top_level.txt
better_hydroponics-0.1.3.dist-info/RECORD
