Metadata-Version: 2.1
Name: better_hydroponics
Version: 0.1.3
Summary: Simulation of hydroponic farming
Author-email: Nils Theeten <nils.theeten@epfl.ch>, Mathieu Penn <mathieu.penn@epfl.ch>
License: MIT License
Project-URL: source, https://github.com/NilsTheeten/hydroponics
Project-URL: tracker, https://github.com/NilsTheeten/hydroponics/issues
Keywords: hydroponics,plant growth,pH calculation,solution solubility,plant simulation,solution maker
Classifier: Development Status :: 3 - Alpha
Classifier: Intended Audience :: Developers
Classifier: License :: OSI Approved :: MIT License
Classifier: Operating System :: OS Independent
Classifier: Programming Language :: Python
Classifier: Programming Language :: Python :: 3
Classifier: Programming Language :: Python :: 3.8
Classifier: Programming Language :: Python :: 3.9
Classifier: Programming Language :: Python :: 3.10
Classifier: Programming Language :: Python :: 3.11
Requires-Python: >=3.10
License-File: LICENSE
Requires-Dist: numpy
Requires-Dist: sympy
Requires-Dist: reportlab
Requires-Dist: pandas
Requires-Dist: matplotlib
Requires-Dist: openpyxl
Requires-Dist: ipython
Provides-Extra: doc
Requires-Dist: furo ; extra == 'doc'
Requires-Dist: myst-parser ; extra == 'doc'
Requires-Dist: sphinx >=5 ; extra == 'doc'
Requires-Dist: sphinx-copybutton ; extra == 'doc'
Provides-Extra: test
Requires-Dist: hypothesis ; extra == 'test'
Requires-Dist: pytest ; extra == 'test'
Requires-Dist: pytest-cov ; extra == 'test'
Requires-Dist: tox ; extra == 'test'
Requires-Dist: genbadge[coverage] ; extra == 'test'
